odoo8_addon_website_mail_snippet_fixed-8.0.1.0.1-py2.7-nspkg.pth
odoo_addons/website_mail_snippet_fixed/__openerp__.py
odoo_addons/website_mail_snippet_fixed/__init__.py
odoo_addons/website_mail_snippet_fixed/README.rst
odoo_addons/website_mail_snippet_fixed/i18n/es.po
odoo_addons/website_mail_snippet_fixed/i18n/sl.po
odoo_addons/website_mail_snippet_fixed/i18n/fr.po
odoo_addons/website_mail_snippet_fixed/views/snippet_hr.xml
odoo_addons/website_mail_snippet_fixed/views/assets.xml
odoo_addons/website_mail_snippet_fixed/views/snippet_2_cols.xml
odoo_addons/website_mail_snippet_fixed/views/snippet_event_date.xml
odoo_addons/website_mail_snippet_fixed/views/snippet_1_col.xml
odoo_addons/website_mail_snippet_fixed/views/snippet_img_text.xml
odoo_addons/website_mail_snippet_fixed/views/templates.xml
odoo_addons/website_mail_snippet_fixed/views/snippet_text_img.xml
odoo_addons/website_mail_snippet_fixed/views/snippet_3_cols.xml
odoo_addons/website_mail_snippet_fixed/images/snippets.png
odoo_addons/website_mail_snippet_fixed/static/description/icon.png
odoo_addons/website_mail_snippet_fixed/static/src/img/snippet_3_cols.png
odoo_addons/website_mail_snippet_fixed/static/src/img/snippet_1_col.png
odoo_addons/website_mail_snippet_fixed/static/src/img/snippet_img_text.png
odoo_addons/website_mail_snippet_fixed/static/src/img/snippet_2_cols.png
odoo_addons/website_mail_snippet_fixed/static/src/img/snippet_text_img.png
odoo_addons/website_mail_snippet_fixed/static/src/img/snippet_hr.png
odoo_addons/website_mail_snippet_fixed/static/src/img/snippet_event_date.png
odoo_addons/website_mail_snippet_fixed/static/src/js/fixed_560px.js
odoo8_addon_website_mail_snippet_fixed-8.0.1.0.1.dist-info/top_level.txt
odoo8_addon_website_mail_snippet_fixed-8.0.1.0.1.dist-info/WHEEL
odoo8_addon_website_mail_snippet_fixed-8.0.1.0.1.dist-info/RECORD
odoo8_addon_website_mail_snippet_fixed-8.0.1.0.1.dist-info/metadata.json
odoo8_addon_website_mail_snippet_fixed-8.0.1.0.1.dist-info/DESCRIPTION.rst
odoo8_addon_website_mail_snippet_fixed-8.0.1.0.1.dist-info/METADATA
odoo8_addon_website_mail_snippet_fixed-8.0.1.0.1.dist-info/namespace_packages.txt
